strictdict/__init__.py
strictdict/api/__init__.py
strictdict/fields/__init__.py
strictdict/simplifiers/__init__.py
strictdict/strictbase/__init__.py
strictdict/strictbase/strictdict.py
strictdict/tests/__init__.py
strictdict/tests/test_fields.py
strictdict/tests/test_strict_dict.py
strictdict/validators/__init__.py
strictdict3-0.4.5.dist-info/DESCRIPTION.rst
strictdict3-0.4.5.dist-info/METADATA
strictdict3-0.4.5.dist-info/RECORD
strictdict3-0.4.5.dist-info/WHEEL
strictdict3-0.4.5.dist-info/metadata.json
strictdict3-0.4.5.dist-info/top_level.txt
